docs/README.md
hledger_args/__init__.py
hledger_args/__main__.py
hledger_args/batch_args.py
hledger_args/cli.py
hledger_args/inter_args.py
hledger_args/lib.py
hledger_args/options.py
tests/__init__.py
venv/bin/rst2html.py
venv/bin/rst2html4.py
venv/bin/rst2html5.py
venv/bin/rst2latex.py
venv/bin/rst2man.py
venv/bin/rst2odt.py
venv/bin/rst2odt_prepstyles.py
venv/bin/rst2pseudoxml.py
venv/bin/rst2s5.py
venv/bin/rst2xetex.py
venv/bin/rst2xml.py
venv/bin/rstpep2html.py
hledger_args-0.1.1.dist-info/METADATA
hledger_args-0.1.1.dist-info/WHEEL
hledger_args-0.1.1.dist-info/entry_points.txt
hledger_args-0.1.1.dist-info/top_level.txt
hledger_args-0.1.1.dist-info/RECORD
