Metadata-Version: 2.1
Name: hledger-args
Version: 0.1.1
License: MIT License
Project-URL: homepage, https://github.com/edkedk99/hledger-args
Project-URL: documentation, https://edkedk99.github.io/hledger-args/
Project-URL: repository, https://github.com/edkedk99/hledger-args
Requires-Python: >=3.8
Requires-Dist: click
Requires-Dist: rich-click
Requires-Dist: questionary
Requires-Dist: fpdf2
